ffiec_data_connect/__init__.py
ffiec_data_connect/async_compatible.py
ffiec_data_connect/config.py
ffiec_data_connect/constants.py
ffiec_data_connect/credentials.py
ffiec_data_connect/data_normalizer.py
ffiec_data_connect/datahelpers.py
ffiec_data_connect/exceptions.py
ffiec_data_connect/ffiec_connection.py
ffiec_data_connect/methods.py
ffiec_data_connect/methods_enhanced.py
ffiec_data_connect/protocol_adapter.py
ffiec_data_connect/py.typed
ffiec_data_connect/soap_cache.py
ffiec_data_connect/utils.py
ffiec_data_connect/xbrl_processor.py
ffiec_data_connect/models/__init__.py
ffiec_data_connect/models/api_models.py
ffiec_data_connect-2.0.5.dist-info/licenses/LICENSE
ffiec_data_connect-2.0.5.dist-info/METADATA
ffiec_data_connect-2.0.5.dist-info/WHEEL
ffiec_data_connect-2.0.5.dist-info/top_level.txt
ffiec_data_connect-2.0.5.dist-info/RECORD
