Metadata-Version: 2.4
Name: ffiec-data-connect
Version: 2.0.5
Summary: Secure, thread-safe Python wrapper for FFIEC webservice API with async support
Author-email: Civic Forge Solutions LLC <michael@civicforge.solutions>
License-Expression: MPL-2.0
Project-URL: Homepage, https://github.com/call-report/ffiec-data-connect
Project-URL: Documentation, https://ffiec-data-connect.readthedocs.io/
Project-URL: Repository, https://github.com/call-report/ffiec-data-connect
Project-URL: Bug Tracker, https://github.com/call-report/ffiec-data-connect/issues
Project-URL: Changelog, https://github.com/call-report/ffiec-data-connect/blob/main/CHANGELOG.md
Keywords: ffiec,banking,financial,regulatory,call-report,ubpr,fdic,async,pandas,polars
Classifier: Development Status :: 4 - Beta
Classifier: Intended Audience :: Financial and Insurance Industry
Classifier: Intended Audience :: Developers
Classifier: Operating System :: OS Independent
Classifier: Programming Language :: Python :: 3
Classifier: Programming Language :: Python :: 3.10
Classifier: Programming Language :: Python :: 3.11
Classifier: Programming Language :: Python :: 3.12
Classifier: Programming Language :: Python :: 3.13
Classifier: Topic :: Office/Business :: Financial
Classifier: Topic :: Software Development :: Libraries :: Python Modules
Classifier: Topic :: Database
Classifier: Typing :: Typed
Requires-Python: >=3.10
License-File: LICENSE
Requires-Dist: requests<3.0.0,>=2.25.0
Requires-Dist: httpx<1.0.0,>=0.24.0
Requires-Dist: pandas<3.0.0,>=1.3.0
Requires-Dist: numpy<3.0.0,>=1.20.0
Requires-Dist: zeep<5.0.0,>=4.0.0
Requires-Dist: lxml<6.0.0,>=4.6.0
Requires-Dist: xmltodict<1.0.0,>=0.12.0
Requires-Dist: defusedxml<1.0.0,>=0.7.0
Requires-Dist: pydantic<3.0.0,>=2.0.0
Provides-Extra: polars
Requires-Dist: polars<1.0.0,>=0.19.0; extra == "polars"
Requires-Dist: pyarrow<20.0.0,>=10.0.0; extra == "polars"
Provides-Extra: dev
Requires-Dist: pytest>=7.0.0; extra == "dev"
Requires-Dist: pytest-asyncio>=0.21.0; extra == "dev"
Requires-Dist: pytest-cov>=4.0.0; extra == "dev"
Requires-Dist: pytest-mock>=3.10.0; extra == "dev"
Requires-Dist: pytest-timeout>=2.1.0; extra == "dev"
Requires-Dist: black>=22.0.0; extra == "dev"
Requires-Dist: isort>=5.10.0; extra == "dev"
Requires-Dist: flake8>=5.0.0; extra == "dev"
Requires-Dist: mypy>=1.0.0; extra == "dev"
Requires-Dist: types-requests>=2.25.0; extra == "dev"
Requires-Dist: psutil>=5.8.0; extra == "dev"
Requires-Dist: sphinx>=5.0.0; extra == "dev"
Requires-Dist: sphinx-rtd-theme>=1.0.0; extra == "dev"
Requires-Dist: coverage>=7.0.0; extra == "dev"
Requires-Dist: build>=0.8.0; extra == "dev"
Requires-Dist: twine>=4.0.0; extra == "dev"
Provides-Extra: docs
Requires-Dist: sphinx>=5.0.0; extra == "docs"
Requires-Dist: sphinx-rtd-theme>=1.0.0; extra == "docs"
Requires-Dist: sphinx-autodoc-typehints>=1.19.0; extra == "docs"
Requires-Dist: myst-parser>=0.18.0; extra == "docs"
Requires-Dist: sphinxcontrib-openapi>=0.7.0; extra == "docs"
Requires-Dist: doc8>=1.1.0; extra == "docs"
Requires-Dist: rstcheck[sphinx]>=6.0.0; extra == "docs"
Requires-Dist: pytest>=7.0.0; extra == "docs"
Requires-Dist: pytest-asyncio>=0.21.0; extra == "docs"
Provides-Extra: notebook
Requires-Dist: jupyter>=1.0.0; extra == "notebook"
Requires-Dist: matplotlib>=3.5.0; extra == "notebook"
Requires-Dist: seaborn>=0.11.0; extra == "notebook"
Provides-Extra: all
Requires-Dist: ffiec-data-connect[dev,docs,notebook,polars]; extra == "all"
Dynamic: license-file
